lint_review/__init__.py
lint_review/__main__.py
lint_review/diff.py
lint_review/gitlab.py
lint_review/reviewer.py
lint_review-0.1.3.dist-info/entry_points.txt
lint_review-0.1.3.dist-info/WHEEL
lint_review-0.1.3.dist-info/METADATA
lint_review-0.1.3.dist-info/RECORD
