Metadata-Version: 2.1
Name: lint-review
Version: 0.1.3
Summary: Code review from any linter!
Home-page: https://gitlab.com/Tadaboody/lint-review
License: MIT
Author: Tomer Keren
Author-email: tomer.keren.dev@gmail.com
Requires-Python: >=3.7,<4.0
Classifier: License :: OSI Approved :: MIT License
Classifier: Programming Language :: Python :: 3
Classifier: Programming Language :: Python :: 3.7
Classifier: Programming Language :: Python :: 3.8
Classifier: Programming Language :: Python :: 3.9
Requires-Dist: more-itertools (>=8.4.0,<9.0.0)
Requires-Dist: python-gitlab (>=2.3.1,<3.0.0)
Requires-Dist: requests (>=2.24.0,<3.0.0)
Project-URL: Repository, https://gitlab.com/Tadaboody/lint-review
